MessageBoxPLUS.py
messageboxplus-0.1.0.dist-info/METADATA
messageboxplus-0.1.0.dist-info/WHEEL
messageboxplus-0.1.0.dist-info/top_level.txt
messageboxplus-0.1.0.dist-info/RECORD
